starro/__init__.py
starro/starro.py
starro/test_starro.py
starro-1.0.10.dist-info/entry_points.txt
starro-1.0.10.dist-info/LICENSE
starro-1.0.10.dist-info/WHEEL
starro-1.0.10.dist-info/METADATA
starro-1.0.10.dist-info/RECORD
