Metadata-Version: 2.1
Name: starro
Version: 1.0.10
Summary: The package objective is to mischaracterize sensitive data from this through blinding masks using asterisk
Home-page: https://github.com/marcosborges/starro-python
Keywords: secury
Author: Marcos Borges
Author-email: contato@marcosborges.com
Requires-Python: >=3.6,<4.0
Classifier: Programming Language :: Python :: 3
Classifier: Programming Language :: Python :: 3.6
Classifier: Programming Language :: Python :: 3.7
Classifier: Programming Language :: Python :: 3.8
Classifier: Programming Language :: Python :: 3.9
Classifier: Topic :: Security
Classifier: Topic :: Software Development :: Libraries :: Python Modules
Classifier: Topic :: System :: Logging
Classifier: Topic :: Text Processing :: Filters
Classifier: Topic :: Text Processing :: General
Classifier: Topic :: Utilities
Project-URL: Documentation, https://github.com/marcosborges/starro-python
Project-URL: Repository, https://github.com/marcosborges/starro-python
